cync.py
cync-1.0.1.dist-info/licenses/LICENSE
cync-1.0.1.dist-info/METADATA
cync-1.0.1.dist-info/WHEEL
cync-1.0.1.dist-info/top_level.txt
cync-1.0.1.dist-info/RECORD
