Metadata-Version: 2.4
Name: cync
Version: 1.0.1
Summary: Local file synchronization tool
Author-email: Zachary Shonk <zacharyshonk@gmail.com>
License-Expression: GPL-3.0+
Project-URL: Homepage, https://github.com/ZacharyShonk/Cync
Project-URL: Issues, https://github.com/ZacharyShonk/Cync/issues
Classifier: Programming Language :: Python :: 3
Classifier: Operating System :: OS Independent
Requires-Python: >=3.11
License-File: LICENSE
Dynamic: license-file
